great_expectations_semantic_types_expectations/__init__.py
great_expectations_semantic_types_expectations/expectations/__init__.py
great_expectations_semantic_types_expectations/expectations/expect_column_values_are_in_language.py
great_expectations_semantic_types_expectations/expectations/expect_column_values_bic_belong_to_country.py
great_expectations_semantic_types_expectations/expectations/expect_column_values_bitcoin_address_positive_balance.py
great_expectations_semantic_types_expectations/expectations/expect_column_values_bitcoin_tx_is_confirmed.py
great_expectations_semantic_types_expectations/expectations/expect_column_values_email_domain_is_not_disposable.py
great_expectations_semantic_types_expectations/expectations/expect_column_values_eth_address_positive_balance.py
great_expectations_semantic_types_expectations/expectations/expect_column_values_imsi_belong_to_country_code.py
great_expectations_semantic_types_expectations/expectations/expect_column_values_ip_address_in_network.py
great_expectations_semantic_types_expectations/expectations/expect_column_values_ip_asn_country_code_in_set.py
great_expectations_semantic_types_expectations/expectations/expect_column_values_ip_is_not_blacklisted.py
great_expectations_semantic_types_expectations/expectations/expect_column_values_password_is_not_leaked.py
great_expectations_semantic_types_expectations/expectations/expect_column_values_to_be_a_non_bot_user_agent.py
great_expectations_semantic_types_expectations/expectations/expect_column_values_to_be_ascii.py
great_expectations_semantic_types_expectations/expectations/expect_column_values_to_be_daytime.py
great_expectations_semantic_types_expectations/expectations/expect_column_values_to_be_fibonacci_number.py
great_expectations_semantic_types_expectations/expectations/expect_column_values_to_be_gtin_base_unit.py
great_expectations_semantic_types_expectations/expectations/expect_column_values_to_be_gtin_variable_measure_trade_item.py
great_expectations_semantic_types_expectations-0.1.0.dist-info/LICENSE
great_expectations_semantic_types_expectations-0.1.0.dist-info/METADATA
great_expectations_semantic_types_expectations-0.1.0.dist-info/WHEEL
great_expectations_semantic_types_expectations-0.1.0.dist-info/top_level.txt
great_expectations_semantic_types_expectations-0.1.0.dist-info/RECORD
