Metadata-Version: 2.1
Name: great-expectations-semantic-types-expectations
Version: 0.1.0
Summary: A collection of Expectations to validate Semantically Typed Data with Great Expectations.
Author: Great Expectations
Author-email: austin@greatexpectations.io
License-File: LICENSE
Requires-Dist: arxiv
Requires-Dist: barcodenumber
Requires-Dist: blockcypher
Requires-Dist: coinaddrvalidator
Requires-Dist: cryptoaddress
Requires-Dist: cryptocompare
Requires-Dist: disposable-email-domains
Requires-Dist: geonamescache
Requires-Dist: great-expectations
Requires-Dist: gtin
Requires-Dist: holidays
Requires-Dist: ipwhois
Requires-Dist: isbnlib
Requires-Dist: langid
Requires-Dist: lxml
Requires-Dist: pgeocode
Requires-Dist: phonenumbers
Requires-Dist: price-parser
Requires-Dist: primefac
Requires-Dist: pwnedpasswords
Requires-Dist: py-moneyed
Requires-Dist: pycountry
Requires-Dist: pydnsbl
Requires-Dist: pyephem
Requires-Dist: python-dateutil
Requires-Dist: python-stdnum
Requires-Dist: pytz
Requires-Dist: pyvat
Requires-Dist: requests
Requires-Dist: schwifty
Requires-Dist: setuptools
Requires-Dist: simple-icd-10
Requires-Dist: sympy
Requires-Dist: us
Requires-Dist: user-agents
Requires-Dist: yahoo-fin
Requires-Dist: zipcodes
